postgresql_deepgeo/__init__.py
postgresql_deepgeo/create.py
postgresql_deepgeo/default.py
postgresql_deepgeo/function.py
postgresql_deepgeo/installer.py
postgresql_deepgeo/url.py
postgresql_extension_installer/__init__.py
postgresql_extension_installer/create.py
postgresql_extension_installer/default.py
postgresql_extension_installer/installer.py
postgresql_extension_installer/loader.py
postgresql_extension_installer/python_package.py
postgresql_extension_installer/query.py
postgresql_extension_installer/url.py
postgresql_extension_installer/util.py
postgresql_extension_installer-0.0.2.dist-info/LICENSE
postgresql_extension_installer-0.0.2.dist-info/METADATA
postgresql_extension_installer-0.0.2.dist-info/WHEEL
postgresql_extension_installer-0.0.2.dist-info/top_level.txt
postgresql_extension_installer-0.0.2.dist-info/RECORD
