Metadata-Version: 2.1
Name: postgresql-extension-installer
Version: 0.0.2
Summary: Easy SQL Extension Installer For PostgreSQL
Home-page: https://github.com/Sotaneum/PostgreSQL-Extension-Installer
Author: Donggun LEE
Author-email: gnyotnu39@gmail.com
License: MIT
Platform: UNKNOWN
Classifier: License :: OSI Approved :: MIT License
